netscaler_module/__init__.py
netscaler_module/nitro.py
netscaler_module-1.3.dist-info/LICENSE
netscaler_module-1.3.dist-info/METADATA
netscaler_module-1.3.dist-info/WHEEL
netscaler_module-1.3.dist-info/top_level.txt
netscaler_module-1.3.dist-info/RECORD
